access_med_tools/CMORise.py
access_med_tools/__init__.py
access_med_tools/_version.py
access_med_tools/app_functions.py
access_med_tools/hackathon.py
access_med_tools/ilamb.py
access_med_tools/master_map.csv
access_med_tools/utilities.py
access_med_tools-0.1.23.dist-info/licenses/LICENSE
access_med_tools-0.1.23.dist-info/METADATA
access_med_tools-0.1.23.dist-info/WHEEL
access_med_tools-0.1.23.dist-info/entry_points.txt
access_med_tools-0.1.23.dist-info/top_level.txt
access_med_tools-0.1.23.dist-info/RECORD
